bits/__init__.py
bits/color/__init__.py
bits_color-1.0.3.dist-info/METADATA
bits_color-1.0.3.dist-info/WHEEL
bits_color-1.0.3.dist-info/top_level.txt
bits_color-1.0.3.dist-info/RECORD
